bibtableau.py
bibtableau-0.1.1.dist-info/METADATA
bibtableau-0.1.1.dist-info/WHEEL
bibtableau-0.1.1.dist-info/RECORD
