Metadata-Version: 2.1
Name: bibtableau
Version: 0.1.1
Summary: Librairie simpliste de manipulation de tableaux a des fins d'enseignement de l'algorithmique
Author: Guy
Author-email: guywiz@gmail.com
Requires-Python: <=3.11
Classifier: Programming Language :: Python :: 2
Classifier: Programming Language :: Python :: 2.7
Classifier: Programming Language :: Python :: 3
Classifier: Programming Language :: Python :: 3.4
Classifier: Programming Language :: Python :: 3.5
Classifier: Programming Language :: Python :: 3.6
Classifier: Programming Language :: Python :: 3.7
Classifier: Programming Language :: Python :: 3.8
Classifier: Programming Language :: Python :: 3.9
Classifier: Programming Language :: Python :: 3.10
Classifier: Programming Language :: Python :: 3.11
